{
  "timestamp": "2024-10-26T07:00:34",
  "url": "https://www.gmx.net/",
  "response": {
    "status": 200
  },
  "scripts": [
    {
      "type": null,
      "src": "https://s.uicdn.com/t/prod/iq/mam/purple/daq.js",
      "id": null,
      "text": null
    },
    {
      "type": null,
      "src": "https://dl.gmx.net/tcf/live/v1/js/tcf-api.js",
      "id": null,
      "text": null
    },
    {
      "type": null,
      "src": "https://img.ui-portal.de/pos-cdn/tracklib/4.7.3/tracklib.poly.min.js",
      "id": null,
      "text": null
    },
    {
      "type": null,
      "src": "https://js.ui-portal.de/homepage/res/legacy/live/1.63/gmx/js/piNctTracking.js",
      "id": null,
      "text": null
    },
    {
      "type": null,
      "src": "https://js.ui-portal.de/homepage/res/legacy/live/1.63/gmx/chunk-vendors.bundle.js",
      "id": null,
      "text": null
    },
    {
      "type": null,
      "src": "https://js.ui-portal.de/homepage/res/legacy/live/1.63/gmx/chunk-common.bundle.js",
      "id": null,
      "text": null
    },
    {
      "type": null,
      "src": "https://js.ui-portal.de/homepage/res/legacy/live/1.63/gmx/homepage.bundle.js",
      "id": null,
      "text": null
    }
  ],
  "articles": [
    {
      "title": "Israel übt Vergeltung gegen den Iran: Wie reagiert Teheran?",
      "url": "https://www.gmx.net/magazine/politik/nahostkonflikt/israel-uebt-vergeltung-iran-teheran-40274300",
      "image_url": "https://i0.gmx.net/image/302/40274302,pd=2,h=300,w=530/nahostkonflikt-iran.jpg",
      "image_title": "Nahostkonflikt - Iran"
    },
    {
      "title": "Heftige Kämpfe im russischen Grenzgebiet Kursk",
      "url": "https://www.gmx.net/magazine/politik/russland-krieg-ukraine/heftige-kaempfe-russischen-grenzgebiet-kursk-40274260",
      "image_url": "https://i0.gmx.net/image/432/40274432,pd=1,h=300,w=530/kursk.jpg",
      "image_title": "Kursk"
    },
    {
      "title": "\"Washington Post\" verzichtet im US-Wahlkampf auf jahrzehntelange Maßnahme",
      "url": "https://www.gmx.net/magazine/politik/wahlen/us-wahl/usa-washington-post-empfehlung-harris-trump-40274370",
      "image_url": "https://i0.gmx.net/image/430/40274430,pd=1,h=300,w=530/zentrale-washington-post-us-hauptstadt.jpg",
      "image_title": "Die Zentrale der \"Washington Post\" in der US-Hauptstadt"
    },
    {
      "title": "Wie das DFB-Team den Europameister überrascht hat",
      "url": "https://www.gmx.net/magazine/sport/fussball/nationalmannschaft/dfb-team-europameister-england-ueberrascht-40274490",
      "image_url": "https://i0.gmx.net/image/524/40274524,pd=1,h=300,w=530/giulia-gwinn.jpg",
      "image_title": "Giulia Gwinn"
    },
    {
      "title": "Bei einem Vergleich schießt Böhmermann übers Ziel hinaus",
      "url": "https://www.gmx.net/magazine/unterhaltung/tv-shows/zdf-magazin-royale-schiesst-boehmermann-uebers-ziel-hinaus-40274454",
      "image_url": "https://i0.gmx.net/image/630/39645630,pd=3,h=300,w=530/jan-boehmermann.jpg",
      "image_title": "Jan Böhmermann"
    },
    {
      "title": "Grateful-Dead-Bassist Phil Lesh mit 84 Jahren gestorben",
      "url": "https://www.gmx.net/magazine/unterhaltung/stars/grateful-dead-bassist-phil-lesh-84-jahren-gestorben-40274526"
    },
    {
      "title": "Überschwemmung in der Wüste",
      "url": "https://www.gmx.net/magazine/panorama/ueberschwemmung-wueste-40273654"
    },
    {
      "title": "Wück im Glück: Debüt-Sieg in Wembley",
      "url": "https://www.gmx.net/magazine/sport/fussball/wueck-glueck-debuet-sieg-wembley-40273988"
    },
    {
      "title": "Kleindienst trifft: Glückliches Remis für Gladbach in Mainz",
      "url": "https://www.gmx.net/magazine/sport/fussball/bundesliga/kleindienst-trifft-glueckliches-remis-gladbach-mainz-40273970"
    },
    {
      "title": "Tierschützer lässt Bär frei – und wird angegriffen",
      "url": "https://www.gmx.net/magazine/panorama/tierschuetzer-laesst-baer-angegriffen-40274516",
      "image_url": "https://i0.gmx.net/image/518/40274518,pd=1,h=170,w=300.jpg"
    },
    {
      "title": "\"Das originalste Original\" sorgt für besonderen Moment bei \"The Voice\"",
      "url": "https://www.gmx.net/magazine/unterhaltung/tv-shows/the-voice-of-germany/originalste-original-sorgt-grossen-moment-the-voice-40272510",
      "image_url": "https://i0.gmx.net/image/542/40272542,pd=1,h=170,w=300/stefani-kai-olaf.jpg",
      "image_title": "Stefani und Kai-Olaf"
    },
    {
      "title": "Selena Gomez spricht über Schönheit und Schattenseiten",
      "url": "https://www.gmx.net/magazine/unterhaltung/stars/selena-gomez-spricht-schoenheit-schattenseiten-40273904",
      "image_url": "https://i0.gmx.net/image/906/40273906,pd=1,h=170,w=300/selena-gomez-spricht-schoenheit-psychische-gesundh.jpg",
      "image_title": "Selena Gomez spricht über Schönheit und psychische Gesundheit."
    },
    {
      "title": "Alec Baldwin: Richterin lehnt Wiederaufnahme von Verfahren ab",
      "url": "https://www.gmx.net/magazine/unterhaltung/stars/alec-baldwin-richterin-lehnt-wiederaufnahme-verfahren-40273796"
    },
    {
      "title": "Klose jubelt weiter: Nürnberg siegt haushoch gegen Regensburg",
      "url": "https://www.gmx.net/magazine/sport/fussball/2-liga/klose-jubelt-nuernberg-siegt-haushoch-regensburg-40273836"
    },
    {
      "title": "Das waren die Highlights der \"Tüll und Tränen\"-Woche",
      "url": "https://www.gmx.net/magazine/unterhaltung/tv-shows/perfekte-dinner-highlights-tuell-traenen-woche-40271922"
    },
    {
      "title": "Nächster Rückschlag: Köln verliert auch gegen Paderborn",
      "url": "https://www.gmx.net/magazine/sport/fussball/2-liga/naechster-rueckschlag-koeln-verliert-paderborn-40273808"
    },
    {
      "title": "Hailey Bieber präsentiert neuen Look mit Anzug und Krawatte",
      "url": "https://www.gmx.net/magazine/unterhaltung/lifestyle/hailey-bieber-praesentiert-look-anzug-krawatte-40273544",
      "image_url": "https://i0.gmx.net/image/546/40273546,pd=1,h=170,w=300/hailey-bieber-justin-bieber-rhode-party.jpg",
      "image_title": "Hailey Bieber und Justin Bieber bei der Rhode-Party."
    },
    {
      "title": "Grateful-Dead-Bassist Phil Lesh mit 84 Jahren gestorben",
      "url": "https://www.gmx.net/magazine/unterhaltung/stars/grateful-dead-bassist-phil-lesh-84-jahren-gestorben-40274526",
      "image_url": "https://i0.gmx.net/image/532/40274532,pd=1,h=170,w=300/phil-lesh.jpg",
      "image_title": "Phil Lesh"
    },
    {
      "title": "Überschwemmung in der Wüste",
      "url": "https://www.gmx.net/magazine/panorama/ueberschwemmung-wueste-40273654"
    },
    {
      "title": "Wück im Glück: Debüt-Sieg in Wembley",
      "url": "https://www.gmx.net/magazine/sport/fussball/wueck-glueck-debuet-sieg-wembley-40273988"
    },
    {
      "title": "Kleindienst trifft: Glückliches Remis für Gladbach in Mainz",
      "url": "https://www.gmx.net/magazine/sport/fussball/bundesliga/kleindienst-trifft-glueckliches-remis-gladbach-mainz-40273970"
    },
    {
      "title": "\"Das originalste Original\" sorgt für besonderen Moment bei \"The Voice\"",
      "url": "https://www.gmx.net/magazine/unterhaltung/tv-shows/the-voice-of-germany/originalste-original-sorgt-grossen-moment-the-voice-40272510"
    },
    {
      "title": "Selena Gomez spricht über Schönheit und Schattenseiten",
      "url": "https://www.gmx.net/magazine/unterhaltung/stars/selena-gomez-spricht-schoenheit-schattenseiten-40273904",
      "image_url": "https://i0.gmx.net/image/906/40273906,pd=1,h=170,w=300/selena-gomez-spricht-schoenheit-psychische-gesundh.jpg",
      "image_title": "Selena Gomez spricht über Schönheit und psychische Gesundheit."
    },
    {
      "title": "Tierschützer lässt Bär frei – und wird angegriffen",
      "url": "https://www.gmx.net/magazine/panorama/tierschuetzer-laesst-baer-angegriffen-40274516",
      "image_url": "https://i0.gmx.net/image/518/40274518,pd=1,h=170,w=300.jpg"
    },
    {
      "title": "Grateful-Dead-Bassist Phil Lesh mit 84 Jahren gestorben",
      "url": "https://www.gmx.net/magazine/unterhaltung/stars/grateful-dead-bassist-phil-lesh-84-jahren-gestorben-40274526"
    },
    {
      "title": "Überschwemmung in der Wüste",
      "url": "https://www.gmx.net/magazine/panorama/ueberschwemmung-wueste-40273654"
    },
    {
      "title": "Wück im Glück: Debüt-Sieg in Wembley",
      "url": "https://www.gmx.net/magazine/sport/fussball/wueck-glueck-debuet-sieg-wembley-40273988"
    },
    {
      "title": "Kleindienst trifft: Glückliches Remis für Gladbach in Mainz",
      "url": "https://www.gmx.net/magazine/sport/fussball/bundesliga/kleindienst-trifft-glueckliches-remis-gladbach-mainz-40273970"
    },
    {
      "title": "Hilfe & Kontakt",
      "teaser": "Hilfestellung & Anleitung zu Ihrem GMX E-Mail Konto",
      "url": "https://hilfe.gmx.net/",
      "image_url": "https://i0.gmx.net/image/518/34288518,pd=2,h=80,w=80.svg"
    },
    {
      "title": "Kundencenter",
      "teaser": "Ihre Daten und Sicherheits-Einstellungen verwalten",
      "url": "https://account.gmx.net/#.pc_page.homepage.index.footer_2.kundencenter",
      "image_url": "https://i0.gmx.net/image/512/34288512,pd=2,h=80,w=80.svg"
    },
    {
      "title": "Passwort vergessen",
      "teaser": "Ihr Passwort zurücksetzen und ein neues anlegen",
      "url": "https://passwort.gmx.net/",
      "image_url": "https://i0.gmx.net/image/522/34288522,pd=2,h=80,w=80.svg"
    },
    {
      "title": "Privatsphäre",
      "teaser": "Alle Informationen zum Datenschutz bei GMX",
      "url": "https://www.gmx.net/datenschutz/#.pc_page.homepage.index.footer_4.datenschutz",
      "image_url": "https://i0.gmx.net/image/524/34288524,pd=2,h=80,w=80.svg"
    },
    {
      "title": "Grateful-Dead-Bassist Phil Lesh mit 84 Jahren gestorben",
      "url": "https://www.gmx.net/magazine/unterhaltung/stars/grateful-dead-bassist-phil-lesh-84-jahren-gestorben-40274526",
      "image_url": "https://i0.gmx.net/image/532/40274532,pd=1,h=170,w=300/phil-lesh.jpg",
      "image_title": "Phil Lesh"
    },
    {
      "title": "Überschwemmung in der Wüste",
      "url": "https://www.gmx.net/magazine/panorama/ueberschwemmung-wueste-40273654"
    },
    {
      "title": "Wück im Glück: Debüt-Sieg in Wembley",
      "url": "https://www.gmx.net/magazine/sport/fussball/wueck-glueck-debuet-sieg-wembley-40273988"
    },
    {
      "title": "Kleindienst trifft: Glückliches Remis für Gladbach in Mainz",
      "url": "https://www.gmx.net/magazine/sport/fussball/bundesliga/kleindienst-trifft-glueckliches-remis-gladbach-mainz-40273970"
    },
    {
      "title": "\"Das originalste Original\" sorgt für besonderen Moment bei \"The Voice\"",
      "url": "https://www.gmx.net/magazine/unterhaltung/tv-shows/the-voice-of-germany/originalste-original-sorgt-grossen-moment-the-voice-40272510"
    }
  ]
}