{
  "timestamp": "2024-07-22T15:00:46",
  "url": "https://www.bild.de/sport/fussball/fussball/home-15769054.bild.html",
  "response": {
    "status": 200
  },
  "scripts": [
    {
      "type": null,
      "src": "https://cmp2.bild.de/unified/wrapperMessagingWithoutDetection.js",
      "id": null,
      "text": null
    },
    {
      "type": null,
      "src": "https://www.asadcdn.com/adlib/pages/bild.js",
      "id": null,
      "text": null
    },
    {
      "type": null,
      "src": "https://rosetta.prod.ps.bild.de/ps-rosetta.js",
      "id": null,
      "text": null
    },
    {
      "type": "text/javascript",
      "src": "https://data-bb21a2f11b.bild.de/iomm/latest/bootstrap/loader.js",
      "id": null,
      "text": null
    },
    {
      "type": null,
      "src": "https://ast.bild.de/bild-bild.de/prod/utag.js",
      "id": null,
      "text": null
    },
    {
      "type": "module",
      "src": "https://a.bildstatic.de/assets/entries/entry-server-routing.VVvN9H4G.js",
      "id": null,
      "text": null
    }
  ],
  "articles": [
    {
      "title": "Abgang nach Spanien: Transfer-Überraschung bei RB Leipzig",
      "url": "https://www.bild.de/sport/fussball/abgang-nach-spanien-transfer-ueberraschung-bei-rb-leipzig-669e65295125e05595d7a9a4"
    },
    {
      "title": "Auftrag an Gladbach-Coach: DIESE 9 Dinge muss Seoane unbedingt ändern!",
      "url": "https://www.bild.de/sport/fussball/borussia-moenchengladbach-diese-9-dinge-muss-seoane-aendern-669e36cda0c414488b77b477"
    },
    {
      "title": "Verrückteste Aktion des Jahres: Fan kommt mit Zimmertür zur Autogrammstunde",
      "url": "https://www.bild.de/sport/fussball/irre-autogrammkarte-fan-liess-spieler-auf-wohnungstuer-unterschreiben-669e49867fb5c155ae673c64"
    }
  ]
}