{
  "timestamp": "2024-08-21T15:01:04",
  "url": "https://www.bild.de/sport/fussball/fussball/home-15769054.bild.html",
  "response": {
    "status": 200
  },
  "scripts": [
    {
      "type": null,
      "src": "https://cmp2.bild.de/unified/wrapperMessagingWithoutDetection.js",
      "id": null,
      "text": null
    },
    {
      "type": null,
      "src": "https://www.asadcdn.com/adlib/pages/bild.js",
      "id": null,
      "text": null
    },
    {
      "type": null,
      "src": "https://rosetta.prod.ps.bild.de/ps-rosetta.js",
      "id": null,
      "text": null
    },
    {
      "type": "text/javascript",
      "src": "https://data-bb21a2f11b.bild.de/iomm/latest/bootstrap/loader.js",
      "id": null,
      "text": null
    },
    {
      "type": null,
      "src": "https://ast.bild.de/bild-bild.de/prod/utag.js",
      "id": null,
      "text": null
    },
    {
      "type": "module",
      "src": "https://a.bildstatic.de/assets/entries/entry-server-routing.9YId1kj6.js",
      "id": null,
      "text": null
    }
  ],
  "articles": [
    {
      "title": "Neue Entwicklung: So steht es beim Transfer von Gosens",
      "url": "https://www.bild.de/sport/fussball/union-berlin-neue-entwicklung-so-steht-es-beim-transfer-von-gosens-66c5ee0a199d30434f6c1e16"
    },
    {
      "title": "Nächster Klub abgesprungen: Jetzt droht Dortmund der Moukoko-GAU!",
      "url": "https://www.bild.de/sport/fussball/bvb-droht-der-moukoko-gau-naechster-klub-abgesprungen-66c5f4c6199d30434f6c1f06"
    },
    {
      "title": "„Wir lieben dich unendlich“: Emotionaler Post von Neuers Anika",
      "url": "https://www.bild.de/sport/fussball/manuel-neuer-tritt-aus-dfb-team-zurueck-emotionaler-post-von-seiner-anika-66c5f313ae4dcc0aa5ca75d5"
    }
  ]
}