{
  "timestamp": "2024-06-29T08:08:17",
  "url": "https://www.bild.de",
  "response": {
    "status": 200
  },
  "scripts": [
    {
      "type": null,
      "src": "https://cmp2.bild.de/unified/wrapperMessagingWithoutDetection.js",
      "id": null,
      "text": null
    },
    {
      "type": null,
      "src": "https://www.asadcdn.com/adlib/pages/bild.js",
      "id": null,
      "text": null
    },
    {
      "type": null,
      "src": "https://rosetta.prod.ps.bild.de/ps-rosetta.js",
      "id": null,
      "text": null
    },
    {
      "type": "text/javascript",
      "src": "https://data-bb21a2f11b.bild.de/iomm/latest/bootstrap/loader.js",
      "id": null,
      "text": null
    },
    {
      "type": null,
      "src": "https://ast.bild.de/bild-bild.de/prod/utag.js",
      "id": null,
      "text": null
    },
    {
      "type": "module",
      "src": "https://a.bildstatic.de/assets/entries/entry-server-routing.VlY6gjtk.js",
      "id": null,
      "text": null
    }
  ],
  "articles": [
    {
      "title": "Wo läuft Schweiz – Italien live im TV?"
    },
    {
      "title": "Sommer zu Schweizer Chancen gegen Italien"
    },
    {
      "title": "Italien-Keeper scherzt über Elferschießen"
    },
    {
      "title": "EM-Torwart in Kneipen-Schlägerei verwickelt?"
    },
    {
      "title": "Ring ist Englands EM-Hoffnung"
    },
    {
      "title": "Maatsen-Wechsel fix!"
    },
    {
      "title": "DFB-Elf darf doch fliegen"
    },
    {
      "title": "Immer wieder Schlagstöcke!"
    },
    {
      "title": "Hälfte der AfD-Politiker jetzt in der Messehalle"
    },
    {
      "title": "Delegierte werden eingekesselt"
    },
    {
      "title": "AfD-Politiker aus Bäckerei befreit"
    },
    {
      "title": "Demonstranten wollen ICE abfangen"
    },
    {
      "title": "AfD-Politiker muss sich in Bäckerei verschanzen"
    },
    {
      "title": "Linken-Aktivistin Carola Rackete unter Demonstranten"
    },
    {
      "title": "Großeinsatz in EssenSchwere Randale vor AfD-Parteitag",
      "url": "https://www.bild.de/politik/inland/grosseinsatz-in-essen-schwere-randale-vor-afd-parteitag-667fbc0500de7a6cf800383b"
    },
    {
      "title": "Comedian darf nicht vor Publikum auftretenLuke Mockridge sagt für TV-Show ab",
      "url": "https://www.bild.de/unterhaltung/tv-fernsehformate/luke-mockridge-sagt-stars-in-der-manege-aufzeichnung-ab-667ee4016f6a605f9b269bad"
    },
    {
      "title": "Formel 1 in ÖsterreichDas Sprint-Rennen im Live-Ticker",
      "url": "https://www.bild.de/sport/mehr-sport/formel-1-in-oesterreich-das-sprint-rennen-im-live-ticker-667ee2ed23778e6a23b2e6f6"
    }
  ]
}