{
  "timestamp": "2024-08-15T17:00:40",
  "url": "https://www.bild.de/news/startseite/news/news-16804530.bild.html",
  "response": {
    "status": 200
  },
  "scripts": [
    {
      "type": null,
      "src": "https://cmp2.bild.de/unified/wrapperMessagingWithoutDetection.js",
      "id": null,
      "text": null
    },
    {
      "type": null,
      "src": "https://www.asadcdn.com/adlib/pages/bild.js",
      "id": null,
      "text": null
    },
    {
      "type": null,
      "src": "https://rosetta.prod.ps.bild.de/ps-rosetta.js",
      "id": null,
      "text": null
    },
    {
      "type": "text/javascript",
      "src": "https://data-bb21a2f11b.bild.de/iomm/latest/bootstrap/loader.js",
      "id": null,
      "text": null
    },
    {
      "type": null,
      "src": "https://ast.bild.de/bild-bild.de/prod/utag.js",
      "id": null,
      "text": null
    },
    {
      "type": "module",
      "src": "https://a.bildstatic.de/assets/entries/entry-server-routing.9fuCh3eq.js",
      "id": null,
      "text": null
    }
  ],
  "articles": [
    {
      "title": "Auf griechischer Insel: Urlauber (48) stirbt nach Biss von Giftspinne",
      "url": "https://www.bild.de/news/ausland/griechenland-urlauber-48-stirbt-nach-biss-von-giftspinne-66bdd16b53073e042f8c9e55"
    },
    {
      "title": "Polizei jagt Jacken-Mann von Cloppenburg: Mädchen (14) von mehreren Tätern vergewaltigt",
      "url": "https://www.bild.de/regional/niedersachsen/maedchen-14-in-cloppenburg-vergewaltigt-polizei-sucht-mann-mit-nfl-jacke-66be0ffbf252a50414e58a0f"
    },
    {
      "title": "Briten rocken in München: Fans hofften bei Coldplay auf „Lucky Dip“-Tickets",
      "url": "https://www.bild.de/regional/muenchen/coldplay-in-muenchen-ausverkauft-fans-hofften-auf-lucky-dip-tickets-669a60a34b9ee64d3870ba0f"
    }
  ]
}