{
  "timestamp": "2024-12-31T13:13:48",
  "url": "https://www.bild.de/politik/startseite/politik/politik-16804552.bild.html",
  "response": {
    "status": 200
  },
  "scripts": [
    {
      "type": null,
      "src": "https://cmp2.bild.de/unified/wrapperMessagingWithoutDetection.js",
      "id": null,
      "text": null
    },
    {
      "type": null,
      "src": "https://www.asadcdn.com/adlib/pages/bild.js",
      "id": null,
      "text": null
    },
    {
      "type": null,
      "src": "https://rosetta.prod.ps.bild.de/ps-rosetta.js",
      "id": null,
      "text": null
    },
    {
      "type": "text/javascript",
      "src": "https://data-bb21a2f11b.bild.de/iomm/latest/bootstrap/loader.js",
      "id": null,
      "text": null
    },
    {
      "type": null,
      "src": "https://ast.bild.de/bild-bild.de/prod/utag.js",
      "id": null,
      "text": null
    },
    {
      "type": "module",
      "src": "https://a.bildstatic.de/assets/entries/entry-server-routing.DeDYCY5q.js",
      "id": null,
      "text": null
    }
  ],
  "articles": [
    {
      "title": "Post von Wagner: Liebes verdammtes Jahr 2024",
      "url": "https://www.bild.de/politik/meinung-kommentare-kolumnen/post-von-wagner-liebes-verdammtes-jahr-2024-6772e6ab5d60421cc7503621"
    },
    {
      "title": "Frankfurter Ethnologin: Silvesternacht ist zum „Freiraum für Gewalt“ geworden",
      "url": "https://www.bild.de/politik/inland/frankfurter-ethnologin-silvesternacht-ist-zum-freiraum-fuer-gewalt-geworden-6772c259b675c340021a8778"
    },
    {
      "title": "Bis 80 Quadratmeter, kein Keller, kleiner Garten: Merz plant Massen-Bau von Mini-Häusern",
      "url": "https://www.bild.de/politik/inland/merz-plant-bau-turbo-programm-fuer-erschwingliche-mini-haeuser-677293605d60421cc7503192"
    }
  ]
}