{
  "timestamp": "2024-03-06T08:01:20",
  "url": "https://m.bild.de/ratgeber/startseite/ratgeber/home-15478376.bildMobile.html",
  "response": {
    "status": 200
  },
  "scripts": [
    {
      "type": null,
      "src": "https://cmp2.bild.de/unified/wrapperMessagingWithoutDetection.js",
      "id": null,
      "text": null
    },
    {
      "type": null,
      "src": "https://www.asadcdn.com/adlib/pages/bild.js",
      "id": null,
      "text": null
    },
    {
      "type": null,
      "src": "https://rosetta.prod.ps.bild.de/ps-rosetta.js",
      "id": null,
      "text": null
    },
    {
      "type": null,
      "src": "https://data-861bbf2127.bild.de/iomm/latest/bootstrap/loader.js",
      "id": null,
      "text": null
    },
    {
      "type": null,
      "src": "https://tags.tiqcdn.com/utag/axelspringer/bild-bild.de/prod/utag.js",
      "id": null,
      "text": null
    },
    {
      "type": "module",
      "src": "https://a.bildstatic.de/assets/entries/entry-server-routing.c6f6e203.js",
      "id": null,
      "text": null
    }
  ],
  "articles": [
    {
      "title": "Fell besteht aus Tausenden ...Horror-Baum erwacht zum Leben",
      "url": "https://m.bild.de/video/clip/news-ausland/haariger-horror-baum-dieses-fell-erwacht-zum-leben-83225416.bildMobile.html"
    },
    {
      "title": "Revolution in der MedizinDiese Spritze macht Millionen Hoffnung",
      "url": "https://m.bild.de/video/clip/ratgeber/migraene-behandlungsmethoden-85946496.bildMobile.html"
    },
    {
      "title": "Alltags-Test mit FußgängerSo gefährlich sind Lastenräder",
      "url": "https://m.bild.de/video/clip/ratgeber/unfallforscher-zeigen-so-gefaehrlich-sind-lastenraeder-wirklich-85807008.bildMobile.html"
    }
  ]
}